ReviewBoard-1.7.29.dist-info/DESCRIPTION.rst
ReviewBoard-1.7.29.dist-info/METADATA
ReviewBoard-1.7.29.dist-info/RECORD
ReviewBoard-1.7.29.dist-info/WHEEL
ReviewBoard-1.7.29.dist-info/dependency_links.txt
ReviewBoard-1.7.29.dist-info/entry_points.txt
ReviewBoard-1.7.29.dist-info/metadata.json
ReviewBoard-1.7.29.dist-info/top_level.txt
reviewboard/__init__.py
reviewboard/__init__.pyc
reviewboard/manage.py
reviewboard/nose.cfg
reviewboard/settings.py
reviewboard/settings.pyc
reviewboard/signals.py
reviewboard/signals.pyc
reviewboard/test.py
reviewboard/urls.py
reviewboard/accounts/__init__.py
reviewboard/accounts/__init__.pyc
reviewboard/accounts/admin.py
reviewboard/accounts/backends.py
reviewboard/accounts/context_processors.py
reviewboard/accounts/decorators.py
reviewboard/accounts/forms.py
reviewboard/accounts/middleware.py
reviewboard/accounts/models.py
reviewboard/accounts/signals.py
reviewboard/accounts/tests.py
reviewboard/accounts/urls.py
reviewboard/accounts/views.py
reviewboard/accounts/evolutions/__init__.py
reviewboard/accounts/evolutions/extra_data.py
reviewboard/accounts/evolutions/is_private.py
reviewboard/accounts/evolutions/localsiteprofile_permissions.py
reviewboard/accounts/evolutions/open_an_issue.py
reviewboard/accounts/evolutions/profile_should_send_email.py
reviewboard/accounts/evolutions/timezone.py
reviewboard/accounts/evolutions/timezone_length_30.py
reviewboard/accounts/fixtures/test_users.json
reviewboard/accounts/sql/profile.sql
reviewboard/admin/__init__.py
reviewboard/admin/__init__.pyc
reviewboard/admin/cache_stats.py
reviewboard/admin/cache_stats.pyc
reviewboard/admin/checks.py
reviewboard/admin/context_processors.py
reviewboard/admin/forms.py
reviewboard/admin/middleware.py
reviewboard/admin/signals.py
reviewboard/admin/signals.pyc
reviewboard/admin/siteconfig.py
reviewboard/admin/support.py
reviewboard/admin/tests.py
reviewboard/admin/urls.py
reviewboard/admin/validation.py
reviewboard/admin/views.py
reviewboard/admin/widgets.py
reviewboard/admin/widgets.pyc
reviewboard/admin/fixtures/initial_evolution_schema.json
reviewboard/admin/management/__init__.py
reviewboard/admin/management/evolutions.py
reviewboard/admin/management/sites.py
reviewboard/admin/management/commands/__init__.py
