Metadata-Version: 2.0
Name: ReviewBoard
Version: 1.7.29
Summary: Review Board, a web-based code review tool
Home-page: https://www.reviewboard.org/
Author: Christian Hammond
Author-email: chipx86@chipx86.com
License: MIT
Download-URL: http://downloads.reviewboard.org/releases/ReviewBoard/1.7/
Platform: UNKNOWN
Classifier: Development Status :: 5 - Production/Stable
Classifier: Environment :: Web Environment
Classifier: Framework :: Django
Classifier: Intended Audience :: Developers
Classifier: License :: OSI Approved :: MIT License
Classifier: Natural Language :: English
Classifier: Operating System :: OS Independent
Classifier: Programming Language :: Python
Classifier: Topic :: Software Development
Classifier: Topic :: Software Development :: Quality Assurance
Requires-Dist: Django (>=1.4.14,<1.5)
Requires-Dist: Djblets (>=0.7.32,<0.8)
Requires-Dist: Pygments (>=1.5)
Requires-Dist: django-evolution (>=0.6.9,<0.6.999)
Requires-Dist: django-pipeline (>=1.2.24,<1.3)
Requires-Dist: docutils
Requires-Dist: markdown (>=2.2.1)
Requires-Dist: mimeparse (>=0.1.3)
Requires-Dist: paramiko (>=1.9.0)
Requires-Dist: python-dateutil (==1.5)
Requires-Dist: python-memcached
Requires-Dist: pytz
Requires-Dist: recaptcha-client
